huscy/attributes/__init__.py
huscy/attributes/admin.py
huscy/attributes/apps.py
huscy/attributes/models.py
huscy/attributes/permissions.py
huscy/attributes/serializer.py
huscy/attributes/services.py
huscy/attributes/urls.py
huscy/attributes/views.py
huscy/attributes/migrations/0001_initial.py
huscy/attributes/migrations/__init__.py
huscy.attributes-1.1.0.dist-info/LICENSE
huscy.attributes-1.1.0.dist-info/METADATA
huscy.attributes-1.1.0.dist-info/WHEEL
huscy.attributes-1.1.0.dist-info/top_level.txt
huscy.attributes-1.1.0.dist-info/RECORD
