Metadata-Version: 2.1
Name: huscy.attributes
Version: 1.1.0
Summary: Managing attributes for subjects in a human research context.
Home-page: https://bitbucket.org/huscy/attributes
Author: Stefan Bunde
Author-email: stefanbunde+git@posteo.de
License: AGPLv3+
Classifier: Development Status :: 5 - Production/Stable
Classifier: License :: OSI Approved :: GNU Affero General Public License v3 or later (AGPLv3+)
Classifier: Operating System :: OS Independent
Classifier: Programming Language :: Python
Classifier: Programming Language :: Python :: 3
Classifier: Programming Language :: Python :: 3 :: Only
Classifier: Programming Language :: Python :: 3.8
Classifier: Programming Language :: Python :: 3.9
Classifier: Programming Language :: Python :: 3.10
Classifier: Programming Language :: Python :: 3.11
Classifier: Programming Language :: Python :: 3.12
Classifier: Framework :: Django
Classifier: Framework :: Django :: 4.2
Classifier: Framework :: Django :: 5.0
Classifier: Framework :: Django :: 5.1
License-File: LICENSE
Requires-Dist: huscy.pseudonyms
Requires-Dist: jsonschema>=4.4
Provides-Extra: development
Requires-Dist: psycopg2-binary; extra == "development"
Provides-Extra: testing
Requires-Dist: tox; extra == "testing"
Requires-Dist: watchdog; extra == "testing"
